pyresumable/__init__.py
pyresumable/resumables.py
pyresumable/tests.py
pyresumable/utils.py
pyresumable-0.0.6.dist-info/METADATA
pyresumable-0.0.6.dist-info/WHEEL
pyresumable-0.0.6.dist-info/licenses/LICENSE
pyresumable-0.0.6.dist-info/RECORD
