Metadata-Version: 2.4
Name: pyresumable
Version: 0.0.6
Summary: A library for creating files chunk-by-chunk
License: BSD-3-Clause
License-File: LICENSE
Author: Leon du Toit
Author-email: l.c.d.toit@usit.uio.no
Requires-Python: >=3.10,<4.0
Classifier: License :: OSI Approved :: BSD License
Classifier: Programming Language :: Python :: 3
Classifier: Programming Language :: Python :: 3.10
Classifier: Programming Language :: Python :: 3.11
Classifier: Programming Language :: Python :: 3.12
Classifier: Programming Language :: Python :: 3.13
Classifier: Programming Language :: Python :: 3.14
Requires-Dist: typing_extensions (>=4.15.0,<5.0.0)
Project-URL: Repository, https://github.com/unioslo/pyresumable
